MANIFEST.in
setup.py
docs/HISTORY.txt
src/dolmen/__init__.py
src/dolmen.app.authentication.egg-info/PKG-INFO
src/dolmen.app.authentication.egg-info/SOURCES.txt
src/dolmen.app.authentication.egg-info/dependency_links.txt
src/dolmen.app.authentication.egg-info/namespace_packages.txt
src/dolmen.app.authentication.egg-info/not-zip-safe
src/dolmen.app.authentication.egg-info/requires.txt
src/dolmen.app.authentication.egg-info/top_level.txt
src/dolmen/app/__init__.py
src/dolmen/app/authentication/README.txt
src/dolmen/app/authentication/__init__.py
src/dolmen/app/authentication/configure.zcml
src/dolmen/app/authentication/interfaces.py
src/dolmen/app/authentication/permissions.py
src/dolmen/app/authentication/browser/__init__.py
src/dolmen/app/authentication/browser/login.py
src/dolmen/app/authentication/browser/logout.py
src/dolmen/app/authentication/browser/management.py
src/dolmen/app/authentication/browser/roles.py
src/dolmen/app/authentication/browser/validation.py
src/dolmen/app/authentication/browser/logout_templates/loggedout.pt
src/dolmen/app/authentication/browser/logout_templates/logout.pt
src/dolmen/app/authentication/browser/management_templates/authsources.pt
src/dolmen/app/authentication/browser/management_templates/manageauth.pt
src/dolmen/app/authentication/locales/de/LC_MESSAGES/dolmen.app.authentication.po
src/dolmen/app/authentication/locales/fr/LC_MESSAGES/dolmen.app.authentication.mo
src/dolmen/app/authentication/locales/fr/LC_MESSAGES/dolmen.app.authentication.po
src/dolmen/app/authentication/plugins/__init__.py
src/dolmen/app/authentication/plugins/cookies.py
src/dolmen/app/authentication/plugins/globalregistry.py
src/dolmen/app/authentication/plugins/principalfolder.py
src/dolmen/app/authentication/tests/__init__.py
src/dolmen/app/authentication/tests/ftesting.zcml
src/dolmen/app/authentication/tests/test_global.py